odoo/addons/procurement_auto_create_group_by_product/README.rst
odoo/addons/procurement_auto_create_group_by_product/__init__.py
odoo/addons/procurement_auto_create_group_by_product/__manifest__.py
odoo/addons/procurement_auto_create_group_by_product/i18n/procurement_auto_create_group_by_product.pot
odoo/addons/procurement_auto_create_group_by_product/models/__init__.py
odoo/addons/procurement_auto_create_group_by_product/models/procurement_group.py
odoo/addons/procurement_auto_create_group_by_product/models/product_product.py
odoo/addons/procurement_auto_create_group_by_product/models/stock_move.py
odoo/addons/procurement_auto_create_group_by_product/models/stock_rule.py
odoo/addons/procurement_auto_create_group_by_product/readme/CONFIGURE.rst
odoo/addons/procurement_auto_create_group_by_product/readme/CONTRIBUTORS.rst
odoo/addons/procurement_auto_create_group_by_product/readme/DESCRIPTION.rst
odoo/addons/procurement_auto_create_group_by_product/static/description/icon.png
odoo/addons/procurement_auto_create_group_by_product/static/description/index.html
odoo/addons/procurement_auto_create_group_by_product/tests/__init__.py
odoo/addons/procurement_auto_create_group_by_product/tests/test_auto_create_by_product.py
odoo/addons/procurement_auto_create_group_by_product/views/procurement_group.xml
odoo/addons/procurement_auto_create_group_by_product/views/stock_rule.xml
odoo14_addon_procurement_auto_create_group_by_product-14.0.1.1.0.dist-info/METADATA
odoo14_addon_procurement_auto_create_group_by_product-14.0.1.1.0.dist-info/WHEEL
odoo14_addon_procurement_auto_create_group_by_product-14.0.1.1.0.dist-info/top_level.txt
odoo14_addon_procurement_auto_create_group_by_product-14.0.1.1.0.dist-info/RECORD
