Metadata-Version: 2.1
Name: odoo14-addon-procurement-auto-create-group-by-product
Version: 14.0.1.1.0
Summary: Generate one picking per product on the procurement run.
Home-page: https://github.com/OCA/stock-logistics-warehouse
Author: BCIM, Odoo Community Association (OCA)
Author-email: support@odoo-community.org
License: AGPL-3
Platform: UNKNOWN
Classifier: Programming Language :: Python
Classifier: Framework :: Odoo
Classifier: Framework :: Odoo :: 14.0
Classifier: License :: OSI Approved :: GNU Affero General Public License v3
Requires-Python: >=3.6
Requires-Dist: odoo14-addon-procurement-auto-create-group
Requires-Dist: odoo <14.1dev,>=14.0a
